stelar_client/__init__.py
stelar_client/admin.py
stelar_client/base.py
stelar_client/catalog.py
stelar_client/client.py
stelar_client/endpoints.py
stelar_client/knowgraph.py
stelar_client/logo.png
stelar_client/model.py
stelar_client/mutils.py
stelar_client/s3.py
stelar_client/test.ipynb
stelar_client/test.py
stelar_client/workflows.py
stelar_client-0.9.1.dist-info/LICENSE
stelar_client-0.9.1.dist-info/METADATA
stelar_client-0.9.1.dist-info/WHEEL
stelar_client-0.9.1.dist-info/top_level.txt
stelar_client-0.9.1.dist-info/RECORD
