Metadata-Version: 2.1
Name: stelar_client
Version: 0.9.1
Summary: A Python client for the STELAR KLMS API.
Home-page: https://github.com/pyscaffold/pyscaffold/
Author: Vasilis Samoladas, Nikolas Bakatselos, Dimitris Petrou
Author-email: vsam@softnet.tuc.gr, nbakatselos@tuc.gr, dpetrou@tuc.gr
License: AGPL
Project-URL: Documentation, https://github.com/stelar-eu/stelar_client/
Project-URL: Source, https://github.com/stelar-eu/stelar_client/
Platform: any
Classifier: Development Status :: 1 - Planning
Classifier: Programming Language :: Python
Classifier: License :: OSI Approved :: GNU Affero General Public License v3 or later (AGPLv3+)
Classifier: Topic :: Database :: Front-Ends
License-File: LICENSE
Requires-Dist: importlib-metadata; python_version < "3.8"
Requires-Dist: requests<3.0,>=2.2
Requires-Dist: minio
Requires-Dist: ipython
Requires-Dist: ipykernel
Requires-Dist: PyYaml
Provides-Extra: testing
Requires-Dist: setuptools; extra == "testing"
Requires-Dist: pytest; extra == "testing"
Requires-Dist: pytest-cov; extra == "testing"
Provides-Extra: dev
Requires-Dist: flake8; extra == "dev"
Requires-Dist: isort; extra == "dev"
Requires-Dist: black; extra == "dev"
Requires-Dist: pyscaffold>=4.6; extra == "dev"
